american_options/AMoption.py
american_options/__init__.py
american_options/jump_diffusion.py
american_options/payoffs.py
american_options/próby.py
american_options/sobol.py
american_options/underlying.py
american_options/xd.py
american_options-0.1.6.dist-info/METADATA
american_options-0.1.6.dist-info/WHEEL
american_options-0.1.6.dist-info/top_level.txt
american_options-0.1.6.dist-info/RECORD
