Metadata-Version: 2.1
Name: american-options
Version: 0.1.6
Summary: Updated plots
Home-page: https://american_options.readthedocs.io/
Author: Przemysław Adamski, Katarzyna Hasal, Kacper Toczek
Author-email: kat.hasal99@gmail.com
Classifier: Intended Audience :: Developers
Classifier: Programming Language :: Python
Classifier: Programming Language :: Python :: 3
Classifier: Programming Language :: Python :: 3.6
Classifier: Programming Language :: Python :: 3.7
Classifier: Programming Language :: Python :: 3.8
Classifier: Programming Language :: Python :: 3.9
Classifier: Operating System :: OS Independent
Requires-Dist: numpy
Requires-Dist: scipy
Requires-Dist: chaospy
Requires-Dist: pandas
Requires-Dist: matplotlib
Requires-Dist: sklearn
Requires-Dist: tqdm
